bb8/__init__.py
bb8/container.py
bb8/core.py
bb8/git.py
bb8/monitor.py
bb8/template.py
bb8/process/__init__.py
bb8/process/cmd.py
bb8/process/exception.py
bb8/script/__init__.py
bb8/script/config.py
bb8/script/failed_mon.py
bb8/script/main.py
bb8/script/mon.py
bb8/script/sync.py
bb8/script/up.py
bb8/script/utils.py
bb8/skill/__init__.py
bb8/skill/cli.py
bb8/task/__init__.py
bb8/task/cli.py
bb8/task/exception.py
bb8/task/manager.py
bb8/utils/__init__.py
bb8/utils/io_utils.py
bb8-0.2.6.dist-info/DESCRIPTION.rst
bb8-0.2.6.dist-info/METADATA
bb8-0.2.6.dist-info/RECORD
bb8-0.2.6.dist-info/WHEEL
bb8-0.2.6.dist-info/entry_points.txt
bb8-0.2.6.dist-info/metadata.json
bb8-0.2.6.dist-info/top_level.txt
