Metadata-Version: 2.0
Name: bb8
Version: 0.2.6
Summary: BB8 - A robot to support developer
Home-page: https://github.com/thongdong7/bb8
Author: Thong Dong
Author-email: thongdong7@gmail.com
License: UNKNOWN
Platform: UNKNOWN
Classifier: Development Status :: 5 - Production/Stable
Classifier: Environment :: Console
Classifier: License :: OSI Approved :: Python Software Foundation License
Classifier: Programming Language :: Python
Classifier: Programming Language :: Python :: 2.6
Classifier: Programming Language :: Python :: 2.7
Classifier: Programming Language :: Python :: 3.3
Classifier: Programming Language :: Python :: 3.4
Classifier: Programming Language :: Python :: 3.5
Requires-Dist: click (==6.6)
Requires-Dist: jinja2 (==2.8)
Requires-Dist: python-dateutil (==2.5.3)
Requires-Dist: pyyaml (==3.11)
Requires-Dist: tornado (==4.3)
